LICENSE
MANIFEST.in
README.rst
grillo.py
setup.py
Grillo.egg-info/PKG-INFO
Grillo.egg-info/SOURCES.txt
Grillo.egg-info/dependency_links.txt
Grillo.egg-info/entry_points.txt
Grillo.egg-info/not-zip-safe
Grillo.egg-info/top_level.txt