Metadata-Version: 1.0
Name: Grillo
Version: 0.1.1
Summary: A terminal based chat server and client.
Home-page: http://github.com/stephenmcd/grillo
Author: Stephen McDonald
Author-email: stephen.mc@gmail.com
License: BSD
Platform: UNKNOWN
Classifier: Development Status :: 4 - Beta
Classifier: Environment :: Console
Classifier: Intended Audience :: Developers
Classifier: Intended Audience :: End Users/Desktop
Classifier: License :: OSI Approved :: BSD License
Classifier: Operating System :: OS Independent
Classifier: Programming Language :: Python
Classifier: Topic :: Communications :: Chat
Classifier: Topic :: Terminals :: Telnet
